octoai/__init__.py
octoai/asset_library/__init__.py
octoai/asset_library/client.py
octoai/asset_library/errors/__init__.py
octoai/asset_library/errors/unprocessable_entity_error.py
octoai/asset_library/types/__init__.py
octoai/asset_library/types/asset.py
octoai/asset_library/types/asset_type.py
octoai/asset_library/types/base_engine.py
octoai/asset_library/types/base_engine_type.py
octoai/asset_library/types/checkpoint_data.py
octoai/asset_library/types/complete_asset_upload_response.py
octoai/asset_library/types/create_asset_response.py
octoai/asset_library/types/create_asset_response_transfer_api.py
octoai/asset_library/types/data.py
octoai/asset_library/types/data_type.py
octoai/asset_library/types/delete_asset_response.py
octoai/asset_library/types/file_data.py
octoai/asset_library/types/file_extension.py
octoai/asset_library/types/file_format.py
octoai/asset_library/types/file_structure.py
octoai/asset_library/types/gcs_oauth_transfer_api.py
octoai/asset_library/types/http_validation_error.py
octoai/asset_library/types/latent_data.py
octoai/asset_library/types/list_assets_response.py
octoai/asset_library/types/list_request_file_format_item.py
octoai/asset_library/types/lora_data.py
octoai/asset_library/types/no_transfer_api.py
octoai/asset_library/types/presigned_url_transfer_api.py
octoai/asset_library/types/retrieve_asset_response.py
octoai/asset_library/types/retrieve_asset_response_transfer_api.py
octoai/asset_library/types/status.py
octoai/asset_library/types/sts_transfer_api.py
octoai/asset_library/types/textual_inversion_data.py
octoai/asset_library/types/transfer_api_type.py
octoai/asset_library/types/vae_data.py
octoai/asset_library/types/validation_error.py
octoai/asset_library/types/validation_error_loc_item.py
octoai/base_client.py
octoai/client.py
octoai/core/__init__.py
octoai/core/api_error.py
octoai/core/client_wrapper.py
octoai/core/datetime_utils.py
octoai/core/file.py
octoai/core/http_client.py
octoai/core/jsonable_encoder.py
octoai-1.11.0.dist-info/METADATA
octoai-1.11.0.dist-info/WHEEL
octoai-1.11.0.dist-info/RECORD
